COPYING.MIT
COPYING.WTFPL
MANIFEST.in
requirements.txt
setup.cfg
setup.py
transmedia/__init__.py
transmedia/conversion.py
transmedia/encoders.py
transmedia/io.py
transmedia/transform_png.py
transmedia/util.py
transmedia.egg-info/PKG-INFO
transmedia.egg-info/SOURCES.txt
transmedia.egg-info/dependency_links.txt
transmedia.egg-info/requires.txt
transmedia.egg-info/top_level.txt
transmedia/tests/__init__.py
transmedia/tests/test_conversion.py
transmedia/tests/test_encoding.py
transmedia/tests/test_imports.py
transmedia/tests/test_io.py