Metadata-Version: 1.1
Name: transmedia
Version: 0.1.6
Summary: utilities for thumbing one's nose at intellectual property     law (or not)
Home-page: https://github.com/jonnystorm/transmedia
Author: jstorm
Author-email: the.jonathan.storm@gmail.com
License: WTFPLv2
Keywords: media conversion audio image copyright trademark hogwash
Platform: UNKNOWN
Classifier: License :: Public Domain
Classifier: Programming Language :: Python
Classifier: Development Status :: 2 - Pre-Alpha
Classifier: Intended Audience :: Other Audience
Classifier: Topic :: Multimedia
